{
    "authors": ["@manuelschneid3r"],
    "description": "File search",
    "description[ar]": "بحث عن ملفات",
    "description[bg]": "Търсене на файлове",
    "description[bs]": "Pretraga datoteka",
    "description[cs]": "Hledání souborů",
    "description[da]": "Fil søgning",
    "description[de]": "Dateisuche",
    "description[el]": "Αναζήτηση αρχείων",
    "description[es]": "Búsqueda de archivos",
    "description[et]": "Failide otsing",
    "description[fi]": "Tiedostohaku",
    "description[fr]": "Recherche de fichiers",
    "description[hi]": "फ़ाइल खोज",
    "description[hr]": "Pretraživanje datoteka",
    "description[hu]": "Fájlkészlet",
    "description[id]": "Pencarian file",
    "description[it]": "Ricerca di file",
    "description[ja]": "ファイル検索",
    "description[ko]": "파일 검색",
    "description[lt]": "Failų paieška",
    "description[lv]": "Failu meklēšana",
    "description[me]": "Pretraga datoteka",
    "description[mk]": "Пребарување на датотеки",
    "description[nl]": "Bestandszoeken",
    "description[no]": "Fil søk",
    "description[pt]": "Pesquisa de arquivos",
    "description[ro]": "Căutare de fișiere",
    "description[ru]": "Поиск файлов",
    "description[sk]": "Vyhľadávanie súborov",
    "description[sl]": "Iskanje datotek",
    "description[sq]": "Kërkimi i skedarëve",
    "description[sr]": "Pretraga datoteka",
    "description[sv]": "Filmsökning",
    "description[th]": "ค้นหาไฟล์",
    "description[tr]": "Dosya arama",
    "description[uk]": "Пошук файлів",
    "description[vi]": "Tìm kiếm tập tin",
    "description[zh]": "文件搜索",
    "license": "ALL",
    "name": "Files",
    "name[ar]": "ملفات",
    "name[bg]": "Файлове",
    "name[bs]": "Datoteke",
    "name[cs]": "Soubory",
    "name[da]": "Filer",
    "name[de]": "Dateien",
    "name[el]": "Αρχεία",
    "name[es]": "Archivos",
    "name[et]": "Failid",
    "name[fi]": "Tiedostot",
    "name[fr]": "Fichiers",
    "name[hi]": "फ़ाइलें",
    "name[hr]": "Datoteke",
    "name[hu]": "Fájlok",
    "name[id]": "Berkas",
    "name[it]": "File",
    "name[ja]": "ファイル",
    "name[ko]": "파일",
    "name[lt]": "Failai",
    "name[lv]": "Faili",
    "name[me]": "Datoteke",
    "name[mk]": "Datoteke",
    "name[nl]": "Bestanden",
    "name[no]": "Filer",
    "name[pt]": "Arquivos",
    "name[ro]": "Fișiere",
    "name[ru]": "Файлы",
    "name[sk]": "Súbory",
    "name[sl]": "Datoteke",
    "name[sq]": "Skedarët",
    "name[sr]": "Datoteke",
    "name[sv]": "Filer",
    "name[th]": "ไฟล์",
    "name[tr]": "Dosyalar",
    "name[uk]": "Файли",
    "name[vi]": "Tệp tin",
    "name[zh]": "文件",
    "url": "https://github.com/albertlauncher/plugins",
}
