{
    "authors": ["@manuelschneid3r"],
    "description": "Lookup definitions in the dictionary",
    "description[ar]": "البحث عن التعريفات في القاموس",
    "description[bg]": "Търсене на дефиниции в речника",
    "description[bs]": "Pretraživanje definicija u rječniku",
    "description[cs]": "Hledat definice ve slovníku",
    "description[da]": "Slå op definitioner i ordbogen",
    "description[de]": "Definitionen im Wörterbuch nachschlagen",
    "description[el]": "Αναζήτηση ορισμών στο λεξικό",
    "description[es]": "Buscar definiciones en el diccionario",
    "description[et]": "Määratluste otsimine sõnaraamatus",
    "description[fi]": "Etsi määritelmiä sanakirjasta",
    "description[fr]": "Rechercher des définitions dans le dictionnaire",
    "description[hi]": "शब्दकोश में परिभाषाएँ देखें",
    "description[hr]": "Pretraživanje definicija u rječniku",
    "description[hu]": "Keresés a szótárban",
    "description[id]": "Mencari definisi dalam kamus",
    "description[it]": "Ricerca definizioni nel dizionario",
    "description[ja]": "辞書で定義を検索",
    "description[ko]": "사전에서 정의 찾기",
    "description[lt]": "Paieška žodyne",
    "description[lv]": "Definīciju meklēšana vārdnīcā",
    "description[me]": "Pretraživanje definicija u rječniku",
    "description[mk]": "Пребарување на дефиниции во речникот",
    "description[nl]": "Definities opzoeken in het woordenboek",
    "description[no]": "Slå opp definisjoner i ordboken",
    "description[pt]": "Procurar definições no dicionário",
    "description[ro]": "Căutarea definițiilor în dicționar",
    "description[ru]": "Поиск определений в словаре",
    "description[sk]": "Hľadanie definícií v slovníku",
    "description[sl]": "Iskanje definicij v slovarju",
    "description[sq]": "Kërko definicionet në fjalor",
    "description[sr]": "Тражење дефиниција у речнику",
    "description[sv]": "Sök definitioner i ordboken",
    "description[th]": "ค้นหาคำจำกัดความในพจนานุกรม",
    "description[tr]": "Sözlükte tanımları ara",
    "description[uk]": "Пошук визначень у словнику",
    "description[vi]": "Tra cứu định nghĩa trong từ điển",
    "description[zh]": "在字典中查找定义",
    "license": "MIT",
    "name": "Dictionary",
    "name[ar]": "قاموس",
    "name[bg]": "Речник",
    "name[bs]": "Rječnik",
    "name[cs]": "Slovník",
    "name[da]": "Ordbog",
    "name[de]": "Wörterbuch",
    "name[el]": "Λεξικό",
    "name[es]": "Diccionario",
    "name[et]": "Sõnastik",
    "name[fi]": "Sanakirja",
    "name[fr]": "Dictionnaire",
    "name[hi]": "शब्दकोश",
    "name[hr]": "Rječnik",
    "name[hu]": "Szótár",
    "name[id]": "Kamus",
    "name[it]": "Dizionario",
    "name[ja]": "辞書",
    "name[ko]": "사전",
    "name[lt]": "Žodynas",
    "name[lv]": "Vārdnīca",
    "name[me]": "Rječnik",
    "name[mk]": "Речник",
    "name[nl]": "Woordenboek",
    "name[no]": "Ordbok",
    "name[pt]": "Dicionário",
    "name[ro]": "Dicționar",
    "name[ru]": "Словарь",
    "name[sk]": "Slovník",
    "name[sl]": "Slovar",
    "name[sq]": "Fjalor",
    "name[sr]": "Речник",
    "name[sv]": "Ordbok",
    "name[th]": "พจนานุกรม",
    "name[tr]": "Sözlük",
    "name[uk]": "Словник",
    "name[vi]": "Từ điển",
    "name[zh]": "字典",
    "url": "https://github.com/albertlauncher/plugins/tree/master/platform_macos",
}
